[
  {
    "id": "bw-1",
    "title": "NM",
    "src": "assets/images/black-and-white/nm.jpg",
    "caption": "NM",
    "description": "Description for NM",
    "medium": "Medium TBD",
    "dimensions": "00\" x 00\""
  },
  {
    "id": "bw-2",
    "title": "Serengeti",
    "src": "assets/images/black-and-white/serengeti.jpg",
    "caption": "Serengeti",
    "description": "Description for Serengeti",
    "medium": "Medium TBD",
    "dimensions": "00\" x 00\""
  },
  {
    "id": "bw-3",
    "title": "Tsunami",
    "src": "assets/images/black-and-white/tsunami.jpg",
    "caption": "Tsunami",
    "description": "Description for Tsunami",
    "medium": "Medium TBD",
    "dimensions": "00\" x 00\""
  },
  {
    "id": "bw-4",
    "title": "Close Encounter",
    "src": "assets/images/black-and-white/close-encounter.jpg",
    "caption": "Close Encounter",
    "description": "Description for Close Encounter",
    "medium": "Medium TBD",
    "dimensions": "00\" x 00\""
  }
]
